myapplication/__init__.py
myapplication/core/mushroomdb/__init__.py
myapplication/core/mushroomdb/body.py
myapplication/core/mushroomdb/gaia.py
myapplication/core/mushroomdb/mycelium.py
myapplication/implementations/FakeMycelium.py
myapplication/implementations/__init__.py
myapplication/implementations/fake_gaya.py
myapplication/main.py
python_boilerplate123123-0.1.1.dist-info/LICENSE
python_boilerplate123123-0.1.1.dist-info/METADATA
python_boilerplate123123-0.1.1.dist-info/WHEEL
python_boilerplate123123-0.1.1.dist-info/entry_points.txt
python_boilerplate123123-0.1.1.dist-info/RECORD
