Metadata-Version: 2.1
Name: python-boilerplate123123
Version: 0.1.1
Summary: Python boilerplate
Home-page: https://github.com/smarlhens/python-boilerplate#readme
License: MIT
Author: Samuel MARLHENS
Author-email: samuel.marlhens@gmail.com
Requires-Python: >=3.11,<4.0
Classifier: License :: OSI Approved :: MIT License
Classifier: Programming Language :: Python :: 3
Classifier: Programming Language :: Python :: 3.11
Classifier: Programming Language :: Python :: 3.12
Requires-Dist: beautifulsoup4 (>=4.12.2,<5.0.0)
Requires-Dist: flask (>=3.0.0,<4.0.0)
Requires-Dist: html-text (>=0.5.2,<0.6.0)
Requires-Dist: kdbai-client (>=0.1.2,<0.2.0)
Requires-Dist: nltk (>=3.8.1,<4.0.0)
Requires-Dist: numpy (>=1.26.2,<2.0.0)
Requires-Dist: pandas (>=2.1.4,<3.0.0)
Requires-Dist: pytest-watch (>=4.2.0,<5.0.0)
Requires-Dist: sentence-transformers (>=2.2.2,<3.0.0)
Requires-Dist: urllib3 (>=2.1.0,<3.0.0)
Project-URL: Repository, https://github.com/smarlhens/python-boilerplate
